presoutput/__init__.py
presoutput/chrome_print.py
presoutput/cli/cli.py
presoutput/pdf_to_pptx.py
presoutput/print_pdf/print_url.py
presoutput/print_pdf/serve_html_file.py
presoutput/quarto_output.py
presoutput/quarto_render.py
presoutput/util/util.py
presoutput-0.1.4.dist-info/METADATA
presoutput-0.1.4.dist-info/WHEEL
presoutput-0.1.4.dist-info/entry_points.txt
presoutput-0.1.4.dist-info/RECORD
