Metadata-Version: 2.1
Name: presoutput
Version: 0.1.4
Summary: Automatically convert your Quarto (qmd) documents into pdf or pptx files for sharing.
Author: aplunket
Author-email: applunket@gmail.com
Requires-Python: >=3.9,<4.0
Classifier: Programming Language :: Python :: 3
Classifier: Programming Language :: Python :: 3.9
Classifier: Programming Language :: Python :: 3.10
Classifier: Programming Language :: Python :: 3.11
Classifier: Programming Language :: Python :: 3.12
Requires-Dist: pdf2image (>=1.17.0,<2.0.0)
Requires-Dist: python-dotenv (>=1.0.1,<2.0.0)
Requires-Dist: python-pptx (>=0.6.23,<0.7.0)
Requires-Dist: requests (>=2.32.3,<3.0.0)
Requires-Dist: websocket-client (>=1.8.0,<2.0.0)
